README.md
setup.cfg
setup.py
sota_dqn/__init__.py
sota_dqn/basic_replay_memory.py
sota_dqn/basic_replay_memory_test.py
sota_dqn/dqn_base.py
sota_dqn/dqn_inference.py
sota_dqn/dqn_trainer.py
sota_dqn.egg-info/PKG-INFO
sota_dqn.egg-info/SOURCES.txt
sota_dqn.egg-info/dependency_links.txt
sota_dqn.egg-info/top_level.txt