Metadata-Version: 2.1
Name: sota-dqn
Version: 0.0.7
Summary: State of the art opinionanted DQN training and inference
Home-page: https://github.com/lukewood/sota-dqn
Author: Luke Wood
Author-email: lukewoodcs@gmail.com
License: MIT
Platform: UNKNOWN
